carbuapi/__init__.py
carbuapi/__main__.py
carbuapi/consts.py
carbuapi-0.0.2.dist-info/METADATA
carbuapi-0.0.2.dist-info/WHEEL
carbuapi-0.0.2.dist-info/entry_points.txt
carbuapi-0.0.2.dist-info/top_level.txt
carbuapi-0.0.2.dist-info/RECORD
