Metadata-Version: 2.1
Name: carbuapi
Version: 0.0.2
Summary: Query fuel prices in Spain
Home-page: https://github.com/ldotlopez/carbuapi
Author: Luis López
Author-email: luis@cuarentaydos.com
License: UNKNOWN
Project-URL: Bug Tracker, https://github.com/ldotlopez/carbuapi/issues
Platform: UNKNOWN
Classifier: Programming Language :: Python :: 3
Classifier: License :: OSI Approved :: MIT License
Classifier: Operating System :: OS Independent
Requires-Python: >=3.9
Requires-Dist: haversine
Requires-Dist: requests
